<?xml version="1.0" encoding="utf-8"?>
<LanguageData>

  <!-- 載具本體 -->

  <RT_Bicycle.label>脚踏车</RT_Bicycle.label>
  <RT_Bicycle.description>人力驱动的双轮车,便宜简易并且使用场景广泛.</RT_Bicycle.description>
  <RT_Bicycle.properties.roles.0.label>骑手</RT_Bicycle.properties.roles.0.label>
  <RT_Bicycle.components.0.label>传动齿轮</RT_Bicycle.components.0.label>
  <RT_Bicycle.components.1.label>结构框架</RT_Bicycle.components.1.label>
  <RT_Bicycle.components.2.label>传动链条</RT_Bicycle.components.2.label>
  <RT_Bicycle.components.3.label>前轮</RT_Bicycle.components.3.label>
  <RT_Bicycle.components.4.label>后稐</RT_Bicycle.components.4.label>


</LanguageData>